mit/__init__.py
mit/__version__.py
mit/api.py
mit/cli.py
mit/core.py
mit/show.py
mit-0.0.6.dist-info/LICENSE
mit-0.0.6.dist-info/METADATA
mit-0.0.6.dist-info/WHEEL
mit-0.0.6.dist-info/entry_points.txt
mit-0.0.6.dist-info/top_level.txt
mit-0.0.6.dist-info/RECORD
