Metadata-Version: 2.1
Name: mit
Version: 0.0.6
Summary: Use mit to Manage iTunes
Home-page: https://pypi.org/project/mit/
Author: Brian Farrell
Author-email: brian.farrell@me.com
License: AGPLv3
Keywords: iTunes ScriptingBridge osx darwin
Platform: UNKNOWN
Classifier: Development Status :: 2 - Pre-Alpha
Classifier: Intended Audience :: End Users/Desktop
Classifier: License :: OSI Approved :: MIT License
Classifier: Topic :: Multimedia :: Sound/Audio
Classifier: Topic :: Multimedia :: Video
Classifier: Topic :: Software Development :: Libraries
Classifier: Environment :: Console
Classifier: Operating System :: MacOS
Classifier: Operating System :: MacOS :: MacOS X
Classifier: Programming Language :: Python
Classifier: Programming Language :: Python :: 3
Classifier: Programming Language :: Python :: 3.6
Classifier: Programming Language :: Python :: 3.7
Classifier: Programming Language :: Python :: Implementation :: CPython
Requires-Python: >=3.6.0
Requires-Dist: pyobjc (>=5.1.1)
